[
    {
      "id": "Hacer mercado",
      "text": "Comprar mercado",
      "done": false
    },
    {
      "id": "Preparar la comida",
      "text": "Preparar los ingredientes",
      "done": false
    },
    {
      "id": "Escuchar musica",
      "text": "Abrir spotify y escuchar música",
      "done": false
    },
    {
      "id": "Ordenar la cocina",
      "text": "Lavar la loza",
      "done": false
    },
    {
      "id": "Estudiar inglés",
      "text": "Hablar inglés hasta tener una convesación fluida",
      "done": false
    }
  ]